Metadata-Version: 1.2
Name: lulzcrypto
Version: 1.0.20
Summary: Simple way for some encrypting.
Home-page: UNKNOWN
Author: LulzLoL231
Author-email: lznet@pm.me
License: UNKNOWN
Project-URL: Source Code, https://github.com/LulzLoL231/lulzcrypto
Keywords: encrypt crypto lulz lulzcrypto pyjwt
Platform: UNKNOWN
